mcp_abc_mock/__init__.py
mcp_abc_mock/__main__.py
mcp_abc_mock/fake_abc_data.csv
mcp_abc_mock/server_stdio.py
mcp_abc_mock/test_mcp_tools_client.py
mcp_abc_mock-0.1.2.dist-info/METADATA
mcp_abc_mock-0.1.2.dist-info/WHEEL
mcp_abc_mock-0.1.2.dist-info/top_level.txt
mcp_abc_mock-0.1.2.dist-info/RECORD
